Workbook

Sheet Dashboard
A1: Business Sales Performance Dashboard (2023-2025)
A2: Source: simulated sales data (Clean_Data sheet). All KPIs are live formulas.
A4: Total Revenue | B4: Total Profit | C4: Profit Margin | D4: Orders | E4: Avg Order Value | F4: 2025 vs 2024
A5: =SUM(Clean_Data!$L$2:$L$5873) | B5: =SUM(Clean_Data!$N$2:$N$5873) | C5: =B5/A5 | D5: =COUNTA(Clean_Data!$A$2:$A$5873) | E5: =A5/D5 | F5: =Yearly!G4

Sheet Clean_Data
A1: OrderID | B1: OrderDate | C1: Month | D1: Year | E1: Region | F1: Category | G1: Product | H1: Segment | I1: Quantity | J1: UnitPrice | K1: Discount | L1: Revenue | M1: Cost | N1: Profit
A2: ORD-05482 | B2: 44927 | C2: 44927 | D2: 2023 | E2: South | F2: Office Supplies | G2: Printer Ink | H2: Consumer | I2: 8 | J2: 62.02 | K2: 0.2 | L2: =I2*J2*(1-K2) | M2: 288 | N2: =L2-M2
A3: ORD-03151 | B3: 44928 | C3: 44927 | D3: 2023 | E3: East | F3: Office Supplies | G3: Paper | H3: Consumer | I3: 4 | J3: 24.12 | K3: 0 | L3: =I3*J3*(1-K3) | M3: 50 | N3: =L3-M3
A4: ORD-04642 | B4: 44928 | C4: 44927 | D4: 2023 | E4: North | F4: Furniture | G4: Bookcase | H4: Consumer | I4: 4 | J4: 174.95 | K4: 0.2 | L4: =I4*J4*(1-K4) | M4: 576 | N4: =L4-M4
A5: ORD-03453 | B5: 44928 | C5: 44927 | D5: 2023 | E5: South | F5: Office Supplies | G5: Binder | H5: Home Office | I5: 6 | J5: 7.89 | K5: 0.1 | L5: =I5*J5*(1-K5) | M5: 19.2 | N5: =L5-M5
A6: ORD-02880 | B6: 44928 | C6: 44927 | D6: 2023 | E6: East | F6: Technology | G6: Keyboard | H6: Corporate | I6: 2 | J6: 46.11 | K6: 0 | L6: =I6*J6*(1-K6) | M6: 49.5 | N6: =L6-M6
A7: ORD-01158 | B7: 44928 | C7: 44927 | D7: 2023 | E7: North | F7: Office Supplies | G7: Pens | H7: Consumer | I7: 6 | J7: 12.1 | K7: 0.3 | L7: =I7*J7*(1-K7) | M7: 32.4 | N7: =L7-M7
A8: ORD-01837 | B8: 44928 | C8: 44927 | D8: 2023 | E8: West | F8: Office Supplies | G8: Printer Ink | H8: Home Office | I8: 9 | J8: 60.73 | K8: 0.1 | L8: =I8*J8*(1-K8) | M8: 324 | N8: =L8-M8
A9: ORD-03503 | B9: 44928 | C9: 44927 | D9: 2023 | E9: South | F9: Office Supplies | G9: Binder | H9: Consumer | I9: 8 | J9: 7.68 | K9: 0.2 | L9: =I9*J9*(1-K9) | M9: 25.6 | N9: =L9-M9
A10: ORD-05540 | B10: 44929 | C10: 44927 | D10: 2023 | E10: South | F10: Office Supplies | G10: Pens | H10: Corporate | I10: 14 | J10: 12.3 | K10: 0.3 | L10: =I10*J10*(1-K10) | M10: 75.6 | N10: =L10-M10
A11: ORD-01221 | B11: 44929 | C11: 44927 | D11: 2023 | E11: West | F11: Technology | G11: Keyboard | H11: Corporate | I11: 3 | J11: 47.12 | K11: 0.05 | L11: =I11*J11*(1-K11) | M11: 74.25 | N11: =L11-M11
A12: ORD-00744 | B12: 44929 | C12: 44927 | D12: 2023 | E12: West | F12: Office Supplies | G12: Stapler | H12: Corporate | I12: 5 | J12: 15.68 | K12: 0.2 | L12: =I12*J12*(1-K12) | M12: 37.5 | N12: =L12-M12
A13: ORD-00741 | B13: 44930 | C13: 44927 | D13: 2023 | E13: East | F13: Office Supplies | G13: Pens | H13: Home Office | I13: 2 | J13: 11.41 | K13: 0 | L13: =I13*J13*(1-K13) | M13: 10.8 | N13: =L13-M13
... A5873: ORD-01109 | B5873: 46022 | C5873: 45992 | D5873: 2025 | E5873: East | F5873: Office Supplies | G5873: Pens | H5873: Home Office | I5873: 15 | J5873: 11.81 | K5873: 0.05 | L5873: =I5873*J5873*(1-K5873) | M5873: 81 | N5873: =L5873-M5873

Sheet Monthly
A1: Monthly | B1: Revenue | C1: Profit | D1: Margin % | E1: Revenue Share | F1: Orders | G1: MoM Growth
A2: 44927 | B2: =SUMIFS(Clean_Data!$L$2:$L$5873,Clean_Data!$C$2:$C$5873,A2) | C2: =SUMIFS(Clean_Data!$N$2:$N$5873,Clean_Data!$C$2:$C$5873,A2) | D2: =IFERROR(C2/B2,0) | E2: =B2/SUM($B$2:$B$37) | F2: =COUNTIFS(Clean_Data!$C$2:$C$5873,A2)
A3: 44958 | B3: =SUMIFS(Clean_Data!$L$2:$L$5873,Clean_Data!$C$2:$C$5873,A3) | C3: =SUMIFS(Clean_Data!$N$2:$N$5873,Clean_Data!$C$2:$C$5873,A3) | D3: =IFERROR(C3/B3,0) | E3: =B3/SUM($B$2:$B$37) | F3: =COUNTIFS(Clean_Data!$C$2:$C$5873,A3) | G3: =IFERROR(B3/B2-1,0)
A4: 44986 | B4: =SUMIFS(Clean_Data!$L$2:$L$5873,Clean_Data!$C$2:$C$5873,A4) | C4: =SUMIFS(Clean_Data!$N$2:$N$5873,Clean_Data!$C$2:$C$5873,A4) | D4: =IFERROR(C4/B4,0) | E4: =B4/SUM($B$2:$B$37) | F4: =COUNTIFS(Clean_Data!$C$2:$C$5873,A4) | G4: =IFERROR(B4/B3-1,0)
A5: 45017 | B5: =SUMIFS(Clean_Data!$L$2:$L$5873,Clean_Data!$C$2:$C$5873,A5) | C5: =SUMIFS(Clean_Data!$N$2:$N$5873,Clean_Data!$C$2:$C$5873,A5) | D5: =IFERROR(C5/B5,0) | E5: =B5/SUM($B$2:$B$37) | F5: =COUNTIFS(Clean_Data!$C$2:$C$5873,A5) | G5: =IFERROR(B5/B4-1,0)
A6: 45047 | B6: =SUMIFS(Clean_Data!$L$2:$L$5873,Clean_Data!$C$2:$C$5873,A6) | C6: =SUMIFS(Clean_Data!$N$2:$N$5873,Clean_Data!$C$2:$C$5873,A6) | D6: =IFERROR(C6/B6,0) | E6: =B6/SUM($B$2:$B$37) | F6: =COUNTIFS(Clean_Data!$C$2:$C$5873,A6) | G6: =IFERROR(B6/B5-1,0)
A7: 45078 | B7: =SUMIFS(Clean_Data!$L$2:$L$5873,Clean_Data!$C$2:$C$5873,A7) | C7: =SUMIFS(Clean_Data!$N$2:$N$5873,Clean_Data!$C$2:$C$5873,A7) | D7: =IFERROR(C7/B7,0) | E7: =B7/SUM($B$2:$B$37) | F7: =COUNTIFS(Clean_Data!$C$2:$C$5873,A7) | G7: =IFERROR(B7/B6-1,0)
A8: 45108 | B8: =SUMIFS(Clean_Data!$L$2:$L$5873,Clean_Data!$C$2:$C$5873,A8) | C8: =SUMIFS(Clean_Data!$N$2:$N$5873,Clean_Data!$C$2:$C$5873,A8) | D8: =IFERROR(C8/B8,0) | E8: =B8/SUM($B$2:$B$37) | F8: =COUNTIFS(Clean_Data!$C$2:$C$5873,A8) | G8: =IFERROR(B8/B7-1,0)
A9: 45139 | B9: =SUMIFS(Clean_Data!$L$2:$L$5873,Clean_Data!$C$2:$C$5873,A9) | C9: =SUMIFS(Clean_Data!$N$2:$N$5873,Clean_Data!$C$2:$C$5873,A9) | D9: =IFERROR(C9/B9,0) | E9: =B9/SUM($B$2:$B$37) | F9: =COUNTIFS(Clean_Data!$C$2:$C$5873,A9) | G9: =IFERROR(B9/B8-1,0)
A10: 45170 | B10: =SUMIFS(Clean_Data!$L$2:$L$5873,Clean_Data!$C$2:$C$5873,A10) | C10: =SUMIFS(Clean_Data!$N$2:$N$5873,Clean_Data!$C$2:$C$5873,A10) | D10: =IFERROR(C10/B10,0) | E10: =B10/SUM($B$2:$B$37) | F10: =COUNTIFS(Clean_Data!$C$2:$C$5873,A10) | G10: =IFERROR(B10/B9-1,0)
A11: 45200 | B11: =SUMIFS(Clean_Data!$L$2:$L$5873,Clean_Data!$C$2:$C$5873,A11) | C11: =SUMIFS(Clean_Data!$N$2:$N$5873,Clean_Data!$C$2:$C$5873,A11) | D11: =IFERROR(C11/B11,0) | E11: =B11/SUM($B$2:$B$37) | F11: =COUNTIFS(Clean_Data!$C$2:$C$5873,A11) | G11: =IFERROR(B11/B10-1,0)
A12: 45231 | B12: =SUMIFS(Clean_Data!$L$2:$L$5873,Clean_Data!$C$2:$C$5873,A12) | C12: =SUMIFS(Clean_Data!$N$2:$N$5873,Clean_Data!$C$2:$C$5873,A12) | D12: =IFERROR(C12/B12,0) | E12: =B12/SUM($B$2:$B$37) | F12: =COUNTIFS(Clean_Data!$C$2:$C$5873,A12) | G12: =IFERROR(B12/B11-1,0)
A13: 45261 | B13: =SUMIFS(Clean_Data!$L$2:$L$5873,Clean_Data!$C$2:$C$5873,A13) | C13: =SUMIFS(Clean_Data!$N$2:$N$5873,Clean_Data!$C$2:$C$5873,A13) | D13: =IFERROR(C13/B13,0) | E13: =B13/SUM($B$2:$B$37) | F13: =COUNTIFS(Clean_Data!$C$2:$C$5873,A13) | G13: =IFERROR(B13/B12-1,0)
A14: 45292 | B14: =SUMIFS(Clean_Data!$L$2:$L$5873,Clean_Data!$C$2:$C$5873,A14) | C14: =SUMIFS(Clean_Data!$N$2:$N$5873,Clean_Data!$C$2:$C$5873,A14) | D14: =IFERROR(C14/B14,0) | E14: =B14/SUM($B$2:$B$37) | F14: =COUNTIFS(Clean_Data!$C$2:$C$5873,A14) | G14: =IFERROR(B14/B13-1,0)
... A37: 45992 | B37: =SUMIFS(Clean_Data!$L$2:$L$5873,Clean_Data!$C$2:$C$5873,A37) | C37: =SUMIFS(Clean_Data!$N$2:$N$5873,Clean_Data!$C$2:$C$5873,A37) | D37: =IFERROR(C37/B37,0) | E37: =B37/SUM($B$2:$B$37) | F37: =COUNTIFS(Clean_Data!$C$2:$C$5873,A37) | G37: =IFERROR(B37/B36-1,0)

Sheet Category
A1: Category | B1: Revenue | C1: Profit | D1: Margin % | E1: Revenue Share | F1: Orders
A2: Technology | B2: =SUMIFS(Clean_Data!$L$2:$L$5873,Clean_Data!$F$2:$F$5873,A2) | C2: =SUMIFS(Clean_Data!$N$2:$N$5873,Clean_Data!$F$2:$F$5873,A2) | D2: =IFERROR(C2/B2,0) | E2: =B2/SUM($B$2:$B$4) | F2: =COUNTIFS(Clean_Data!$F$2:$F$5873,A2)
A3: Furniture | B3: =SUMIFS(Clean_Data!$L$2:$L$5873,Clean_Data!$F$2:$F$5873,A3) | C3: =SUMIFS(Clean_Data!$N$2:$N$5873,Clean_Data!$F$2:$F$5873,A3) | D3: =IFERROR(C3/B3,0) | E3: =B3/SUM($B$2:$B$4) | F3: =COUNTIFS(Clean_Data!$F$2:$F$5873,A3)
A4: Office Supplies | B4: =SUMIFS(Clean_Data!$L$2:$L$5873,Clean_Data!$F$2:$F$5873,A4) | C4: =SUMIFS(Clean_Data!$N$2:$N$5873,Clean_Data!$F$2:$F$5873,A4) | D4: =IFERROR(C4/B4,0) | E4: =B4/SUM($B$2:$B$4) | F4: =COUNTIFS(Clean_Data!$F$2:$F$5873,A4)

Sheet Region
A1: Region | B1: Revenue | C1: Profit | D1: Margin % | E1: Revenue Share | F1: Orders
A2: West | B2: =SUMIFS(Clean_Data!$L$2:$L$5873,Clean_Data!$E$2:$E$5873,A2) | C2: =SUMIFS(Clean_Data!$N$2:$N$5873,Clean_Data!$E$2:$E$5873,A2) | D2: =IFERROR(C2/B2,0) | E2: =B2/SUM($B$2:$B$5) | F2: =COUNTIFS(Clean_Data!$E$2:$E$5873,A2)
A3: East | B3: =SUMIFS(Clean_Data!$L$2:$L$5873,Clean_Data!$E$2:$E$5873,A3) | C3: =SUMIFS(Clean_Data!$N$2:$N$5873,Clean_Data!$E$2:$E$5873,A3) | D3: =IFERROR(C3/B3,0) | E3: =B3/SUM($B$2:$B$5) | F3: =COUNTIFS(Clean_Data!$E$2:$E$5873,A3)
A4: South | B4: =SUMIFS(Clean_Data!$L$2:$L$5873,Clean_Data!$E$2:$E$5873,A4) | C4: =SUMIFS(Clean_Data!$N$2:$N$5873,Clean_Data!$E$2:$E$5873,A4) | D4: =IFERROR(C4/B4,0) | E4: =B4/SUM($B$2:$B$5) | F4: =COUNTIFS(Clean_Data!$E$2:$E$5873,A4)
A5: North | B5: =SUMIFS(Clean_Data!$L$2:$L$5873,Clean_Data!$E$2:$E$5873,A5) | C5: =SUMIFS(Clean_Data!$N$2:$N$5873,Clean_Data!$E$2:$E$5873,A5) | D5: =IFERROR(C5/B5,0) | E5: =B5/SUM($B$2:$B$5) | F5: =COUNTIFS(Clean_Data!$E$2:$E$5873,A5)

Sheet Products
A1: Products | B1: Revenue | C1: Profit | D1: Margin % | E1: Revenue Share | F1: Orders
A2: Laptop | B2: =SUMIFS(Clean_Data!$L$2:$L$5873,Clean_Data!$G$2:$G$5873,A2) | C2: =SUMIFS(Clean_Data!$N$2:$N$5873,Clean_Data!$G$2:$G$5873,A2) | D2: =IFERROR(C2/B2,0) | E2: =B2/SUM($B$2:$B$15) | F2: =COUNTIFS(Clean_Data!$G$2:$G$5873,A2)
A3: Smartphone | B3: =SUMIFS(Clean_Data!$L$2:$L$5873,Clean_Data!$G$2:$G$5873,A3) | C3: =SUMIFS(Clean_Data!$N$2:$N$5873,Clean_Data!$G$2:$G$5873,A3) | D3: =IFERROR(C3/B3,0) | E3: =B3/SUM($B$2:$B$15) | F3: =COUNTIFS(Clean_Data!$G$2:$G$5873,A3)
A4: Printer Ink | B4: =SUMIFS(Clean_Data!$L$2:$L$5873,Clean_Data!$G$2:$G$5873,A4) | C4: =SUMIFS(Clean_Data!$N$2:$N$5873,Clean_Data!$G$2:$G$5873,A4) | D4: =IFERROR(C4/B4,0) | E4: =B4/SUM($B$2:$B$15) | F4: =COUNTIFS(Clean_Data!$G$2:$G$5873,A4)
A5: Desk | B5: =SUMIFS(Clean_Data!$L$2:$L$5873,Clean_Data!$G$2:$G$5873,A5) | C5: =SUMIFS(Clean_Data!$N$2:$N$5873,Clean_Data!$G$2:$G$5873,A5) | D5: =IFERROR(C5/B5,0) | E5: =B5/SUM($B$2:$B$15) | F5: =COUNTIFS(Clean_Data!$G$2:$G$5873,A5)
A6: Paper | B6: =SUMIFS(Clean_Data!$L$2:$L$5873,Clean_Data!$G$2:$G$5873,A6) | C6: =SUMIFS(Clean_Data!$N$2:$N$5873,Clean_Data!$G$2:$G$5873,A6) | D6: =IFERROR(C6/B6,0) | E6: =B6/SUM($B$2:$B$15) | F6: =COUNTIFS(Clean_Data!$G$2:$G$5873,A6)
A7: Sofa | B7: =SUMIFS(Clean_Data!$L$2:$L$5873,Clean_Data!$G$2:$G$5873,A7) | C7: =SUMIFS(Clean_Data!$N$2:$N$5873,Clean_Data!$G$2:$G$5873,A7) | D7: =IFERROR(C7/B7,0) | E7: =B7/SUM($B$2:$B$15) | F7: =COUNTIFS(Clean_Data!$G$2:$G$5873,A7)
A8: Office Chair | B8: =SUMIFS(Clean_Data!$L$2:$L$5873,Clean_Data!$G$2:$G$5873,A8) | C8: =SUMIFS(Clean_Data!$N$2:$N$5873,Clean_Data!$G$2:$G$5873,A8) | D8: =IFERROR(C8/B8,0) | E8: =B8/SUM($B$2:$B$15) | F8: =COUNTIFS(Clean_Data!$G$2:$G$5873,A8)
A9: Monitor | B9: =SUMIFS(Clean_Data!$L$2:$L$5873,Clean_Data!$G$2:$G$5873,A9) | C9: =SUMIFS(Clean_Data!$N$2:$N$5873,Clean_Data!$G$2:$G$5873,A9) | D9: =IFERROR(C9/B9,0) | E9: =B9/SUM($B$2:$B$15) | F9: =COUNTIFS(Clean_Data!$G$2:$G$5873,A9)
A10: Bookcase | B10: =SUMIFS(Clean_Data!$L$2:$L$5873,Clean_Data!$G$2:$G$5873,A10) | C10: =SUMIFS(Clean_Data!$N$2:$N$5873,Clean_Data!$G$2:$G$5873,A10) | D10: =IFERROR(C10/B10,0) | E10: =B10/SUM($B$2:$B$15) | F10: =COUNTIFS(Clean_Data!$G$2:$G$5873,A10)
A11: Pens | B11: =SUMIFS(Clean_Data!$L$2:$L$5873,Clean_Data!$G$2:$G$5873,A11) | C11: =SUMIFS(Clean_Data!$N$2:$N$5873,Clean_Data!$G$2:$G$5873,A11) | D11: =IFERROR(C11/B11,0) | E11: =B11/SUM($B$2:$B$15) | F11: =COUNTIFS(Clean_Data!$G$2:$G$5873,A11)
A12: Headphones | B12: =SUMIFS(Clean_Data!$L$2:$L$5873,Clean_Data!$G$2:$G$5873,A12) | C12: =SUMIFS(Clean_Data!$N$2:$N$5873,Clean_Data!$G$2:$G$5873,A12) | D12: =IFERROR(C12/B12,0) | E12: =B12/SUM($B$2:$B$15) | F12: =COUNTIFS(Clean_Data!$G$2:$G$5873,A12)
A13: Binder | B13: =SUMIFS(Clean_Data!$L$2:$L$5873,Clean_Data!$G$2:$G$5873,A13) | C13: =SUMIFS(Clean_Data!$N$2:$N$5873,Clean_Data!$G$2:$G$5873,A13) | D13: =IFERROR(C13/B13,0) | E13: =B13/SUM($B$2:$B$15) | F13: =COUNTIFS(Clean_Data!$G$2:$G$5873,A13)
... A15: Keyboard | B15: =SUMIFS(Clean_Data!$L$2:$L$5873,Clean_Data!$G$2:$G$5873,A15) | C15: =SUMIFS(Clean_Data!$N$2:$N$5873,Clean_Data!$G$2:$G$5873,A15) | D15: =IFERROR(C15/B15,0) | E15: =B15/SUM($B$2:$B$15) | F15: =COUNTIFS(Clean_Data!$G$2:$G$5873,A15)

Sheet Yearly
A1: Yearly | B1: Revenue | C1: Profit | D1: Margin % | E1: Revenue Share | F1: Orders | G1: YoY Growth
A2: 2023 | B2: =SUMIFS(Clean_Data!$L$2:$L$5873,Clean_Data!$D$2:$D$5873,A2) | C2: =SUMIFS(Clean_Data!$N$2:$N$5873,Clean_Data!$D$2:$D$5873,A2) | D2: =IFERROR(C2/B2,0) | E2: =B2/SUM($B$2:$B$4) | F2: =COUNTIFS(Clean_Data!$D$2:$D$5873,A2)
A3: 2024 | B3: =SUMIFS(Clean_Data!$L$2:$L$5873,Clean_Data!$D$2:$D$5873,A3) | C3: =SUMIFS(Clean_Data!$N$2:$N$5873,Clean_Data!$D$2:$D$5873,A3) | D3: =IFERROR(C3/B3,0) | E3: =B3/SUM($B$2:$B$4) | F3: =COUNTIFS(Clean_Data!$D$2:$D$5873,A3) | G3: =B3/B2-1
A4: 2025 | B4: =SUMIFS(Clean_Data!$L$2:$L$5873,Clean_Data!$D$2:$D$5873,A4) | C4: =SUMIFS(Clean_Data!$N$2:$N$5873,Clean_Data!$D$2:$D$5873,A4) | D4: =IFERROR(C4/B4,0) | E4: =B4/SUM($B$2:$B$4) | F4: =COUNTIFS(Clean_Data!$D$2:$D$5873,A4) | G4: =B4/B3-1

Sheet Discount
A1: Discount | B1: Revenue | C1: Profit | D1: Margin % | E1: Revenue Share | F1: Orders
A2: 0 | B2: =SUMIFS(Clean_Data!$L$2:$L$5873,Clean_Data!$K$2:$K$5873,A2) | C2: =SUMIFS(Clean_Data!$N$2:$N$5873,Clean_Data!$K$2:$K$5873,A2) | D2: =IFERROR(C2/B2,0) | E2: =B2/SUM($B$2:$B$6) | F2: =COUNTIFS(Clean_Data!$K$2:$K$5873,A2)
A3: 0.05 | B3: =SUMIFS(Clean_Data!$L$2:$L$5873,Clean_Data!$K$2:$K$5873,A3) | C3: =SUMIFS(Clean_Data!$N$2:$N$5873,Clean_Data!$K$2:$K$5873,A3) | D3: =IFERROR(C3/B3,0) | E3: =B3/SUM($B$2:$B$6) | F3: =COUNTIFS(Clean_Data!$K$2:$K$5873,A3)
A4: 0.1 | B4: =SUMIFS(Clean_Data!$L$2:$L$5873,Clean_Data!$K$2:$K$5873,A4) | C4: =SUMIFS(Clean_Data!$N$2:$N$5873,Clean_Data!$K$2:$K$5873,A4) | D4: =IFERROR(C4/B4,0) | E4: =B4/SUM($B$2:$B$6) | F4: =COUNTIFS(Clean_Data!$K$2:$K$5873,A4)
A5: 0.2 | B5: =SUMIFS(Clean_Data!$L$2:$L$5873,Clean_Data!$K$2:$K$5873,A5) | C5: =SUMIFS(Clean_Data!$N$2:$N$5873,Clean_Data!$K$2:$K$5873,A5) | D5: =IFERROR(C5/B5,0) | E5: =B5/SUM($B$2:$B$6) | F5: =COUNTIFS(Clean_Data!$K$2:$K$5873,A5)
A6: 0.3 | B6: =SUMIFS(Clean_Data!$L$2:$L$5873,Clean_Data!$K$2:$K$5873,A6) | C6: =SUMIFS(Clean_Data!$N$2:$N$5873,Clean_Data!$K$2:$K$5873,A6) | D6: =IFERROR(C6/B6,0) | E6: =B6/SUM($B$2:$B$6) | F6: =COUNTIFS(Clean_Data!$K$2:$K$5873,A6)

Sheet Region_x_Category
A1: Profit margin % | B1: Furniture | C1: Office Supplies | D1: Technology
A2: East | B2: =IFERROR(SUMIFS(Clean_Data!$N$2:$N$5873,Clean_Data!$E$2:$E$5873,$A2,Clean_Data!$F$2:$F$5873,B$1)/SUMIFS(Clean_Data!$L$2:$L$5873,Clean_Data!$E$2:$E$5873,$A2,Clean_Data!$F$2:$F$5873,B$1),0) | C2: =IFERROR(SUMIFS(Clean_Data!$N$2:$N$5873,Clean_Data!$E$2:$E$5873,$A2,Clean_Data!$F$2:$F$5873,C$1)/SUMIFS(Clean_Data!$L$2:$L$5873,Clean_Data!$E$2:$E$5873,$A2,Clean_Data!$F$2:$F$5873,C$1),0) | D2: =IFERROR(SUMIFS(Clean_Data!$N$2:$N$5873,Clean_Data!$E$2:$E$5873,$A2,Clean_Data!$F$2:$F$5873,D$1)/SUMIFS(Clean_Data!$L$2:$L$5873,Clean_Data!$E$2:$E$5873,$A2,Clean_Data!$F$2:$F$5873,D$1),0)
A3: North | B3: =IFERROR(SUMIFS(Clean_Data!$N$2:$N$5873,Clean_Data!$E$2:$E$5873,$A3,Clean_Data!$F$2:$F$5873,B$1)/SUMIFS(Clean_Data!$L$2:$L$5873,Clean_Data!$E$2:$E$5873,$A3,Clean_Data!$F$2:$F$5873,B$1),0) | C3: =IFERROR(SUMIFS(Clean_Data!$N$2:$N$5873,Clean_Data!$E$2:$E$5873,$A3,Clean_Data!$F$2:$F$5873,C$1)/SUMIFS(Clean_Data!$L$2:$L$5873,Clean_Data!$E$2:$E$5873,$A3,Clean_Data!$F$2:$F$5873,C$1),0) | D3: =IFERROR(SUMIFS(Clean_Data!$N$2:$N$5873,Clean_Data!$E$2:$E$5873,$A3,Clean_Data!$F$2:$F$5873,D$1)/SUMIFS(Clean_Data!$L$2:$L$5873,Clean_Data!$E$2:$E$5873,$A3,Clean_Data!$F$2:$F$5873,D$1),0)
A4: South | B4: =IFERROR(SUMIFS(Clean_Data!$N$2:$N$5873,Clean_Data!$E$2:$E$5873,$A4,Clean_Data!$F$2:$F$5873,B$1)/SUMIFS(Clean_Data!$L$2:$L$5873,Clean_Data!$E$2:$E$5873,$A4,Clean_Data!$F$2:$F$5873,B$1),0) | C4: =IFERROR(SUMIFS(Clean_Data!$N$2:$N$5873,Clean_Data!$E$2:$E$5873,$A4,Clean_Data!$F$2:$F$5873,C$1)/SUMIFS(Clean_Data!$L$2:$L$5873,Clean_Data!$E$2:$E$5873,$A4,Clean_Data!$F$2:$F$5873,C$1),0) | D4: =IFERROR(SUMIFS(Clean_Data!$N$2:$N$5873,Clean_Data!$E$2:$E$5873,$A4,Clean_Data!$F$2:$F$5873,D$1)/SUMIFS(Clean_Data!$L$2:$L$5873,Clean_Data!$E$2:$E$5873,$A4,Clean_Data!$F$2:$F$5873,D$1),0)
A5: West | B5: =IFERROR(SUMIFS(Clean_Data!$N$2:$N$5873,Clean_Data!$E$2:$E$5873,$A5,Clean_Data!$F$2:$F$5873,B$1)/SUMIFS(Clean_Data!$L$2:$L$5873,Clean_Data!$E$2:$E$5873,$A5,Clean_Data!$F$2:$F$5873,B$1),0) | C5: =IFERROR(SUMIFS(Clean_Data!$N$2:$N$5873,Clean_Data!$E$2:$E$5873,$A5,Clean_Data!$F$2:$F$5873,C$1)/SUMIFS(Clean_Data!$L$2:$L$5873,Clean_Data!$E$2:$E$5873,$A5,Clean_Data!$F$2:$F$5873,C$1),0) | D5: =IFERROR(SUMIFS(Clean_Data!$N$2:$N$5873,Clean_Data!$E$2:$E$5873,$A5,Clean_Data!$F$2:$F$5873,D$1)/SUMIFS(Clean_Data!$L$2:$L$5873,Clean_Data!$E$2:$E$5873,$A5,Clean_Data!$F$2:$F$5873,D$1),0)

Sheet Insights
A1: Key Insights
A3: 1. Total revenue is 2,321,963 with profit 465,935 (overall margin 20.1%) from 5,872 order lines.
A4: 2. Revenue grew 16.2% in 2024 and 11.1% in 2025 - steady growth.
A5: 3. Technology is the top category by revenue (48.7% of sales); Office Supplies has the best margin (43.3%).
A6: 4. Furniture has the weakest margin (1.9%) - discounting is hurting it.
A7: 5. West is the top region (32.2% of revenue); South has the lowest margin (17.4%) because of heavier discounts.
A8: 6. Seasonality: Oct-Dec (Q4) brings 33.8% of yearly revenue; best month is December, weakest is January.
A9: 7. Top 3 products (Laptop, Smartphone, Printer Ink) give 48.6% of revenue.
A10: 8. Orders with 20%+ discount earn only 0.2% margin vs 29.4% with no discount.
A11: 9. Furniture sold at 20%+ discount is loss-making (profit -33,475).
A14: Recommendations
A16: 1. Cap discounts at 10% for Furniture and review pricing on Sofa/Desk - protect margin.
... A23: Note: figures in the text are from the Python analysis of the same Clean_Data sheet; dataset is simulated.

Sheet Cleaning_Log
A1: Cleaning step | B1: Rows
A2: Raw rows | B2: 6180
A3: Duplicate rows removed | B3: 180
A4: Rows with missing Region removed | B4: 90
A5: Rows with invalid (<=0) Quantity removed | B5: 38
A6: Clean rows | B6: 5872
